setup.py
VideoDataVideoData.egg-info/PKG-INFO
VideoDataVideoData.egg-info/SOURCES.txt
VideoDataVideoData.egg-info/dependency_links.txt
VideoDataVideoData.egg-info/top_level.txt
api/__init__.py
api/video_data_api.py
models/__init__.py
models/body.py
models/description.py
models/error_code.py
models/extra_body.py
models/inline_response200.py
models/inline_response200_data.py
models/video.py
models/video_statistics.py